pkg/__init__.py
pkg/tr.py
hmkshub_kmeans-0.1.2.dist-info/LICENSE.txt
hmkshub_kmeans-0.1.2.dist-info/METADATA
hmkshub_kmeans-0.1.2.dist-info/WHEEL
hmkshub_kmeans-0.1.2.dist-info/top_level.txt
hmkshub_kmeans-0.1.2.dist-info/RECORD
