Metadata-Version: 2.1
Name: hmkshub-kmeans
Version: 0.1.2
Summary: A python package to K-means clustring
Home-page: https://github.com/Herambdata/dl-package
Author: Heramb Mishra
Author-email: heramb1008@gmail.com
License: MIT
Platform: UNKNOWN
Requires-Dist: numpy (>=1.18.5)
Requires-Dist: pandas (>=1.0.5)
Requires-Dist: scikit-learn (>=0.23.1)
